CODEOWNERS
LICENSE.TXT
MANIFEST.in
README.md
requirements-dev.txt
setup.cfg
setup.py
flake8_koles/__about__.py
flake8_koles/__init__.py
flake8_koles/checker.py
flake8_koles.egg-info/PKG-INFO
flake8_koles.egg-info/SOURCES.txt
flake8_koles.egg-info/dependency_links.txt
flake8_koles.egg-info/entry_points.txt
flake8_koles.egg-info/requires.txt
flake8_koles.egg-info/top_level.txt
flake8_koles/data/swear_list/english.dat
flake8_koles/data/swear_list/polish.dat
tests/conftest.py
tests/test_checker.py