Metadata-Version: 2.1
Name: flake8-koles
Version: 0.2.1
Summary: Watch your language young lad! Swears and curses linter.
Home-page: https://pypi.org/project/flake8-koles/
Author: myslak71
Author-email: myslak@protonmail.com
License: MIT
Download-URL: https://github.com/myslak71/flake8-koles/archive/v0.2.1.tar.gz
Keywords: linter,flake8,swears,curses,extension,koles
Platform: UNKNOWN
Classifier: Development Status :: 3 - Alpha
Classifier: Intended Audience :: Developers
Classifier: Natural Language :: English
Classifier: License :: OSI Approved :: MIT License
Classifier: Programming Language :: Python
Classifier: Programming Language :: Python :: 3.6
Classifier: Programming Language :: Python :: 3.7
Requires-Python: >=3.6
Provides-Extra: dev
